xai_gpt_shap/ChatGptClient.py
xai_gpt_shap/ShapCalculator.py
xai_gpt_shap/__init__.py
xai_gpt_shap/roles.py
xai_gpt_shap-1.0.6.dist-info/METADATA
xai_gpt_shap-1.0.6.dist-info/WHEEL
xai_gpt_shap-1.0.6.dist-info/entry_points.txt
xai_gpt_shap-1.0.6.dist-info/RECORD
