Metadata-Version: 2.3
Name: xai-gpt-shap
Version: 1.0.6
Summary: A library for explainable AI with SHAP and GPT-based explanations.
Home-page: https://github.com/JanHuntersi/xai_gpt_shap
License: MIT
Author: (JanHuntersi)
Requires-Python: >=3.11,<4.0
Classifier: License :: OSI Approved :: MIT License
Classifier: Programming Language :: Python :: 3
Classifier: Programming Language :: Python :: 3.11
Classifier: Programming Language :: Python :: 3.12
Classifier: Programming Language :: Python :: 3.13
Requires-Dist: matplotlib (>=3.10.0,<4.0.0)
Requires-Dist: onnxruntime (>=1.20.1,<2.0.0)
Requires-Dist: openai (>=1.57.2,<2.0.0)
Requires-Dist: pandas (>=2.2.3,<3.0.0)
Requires-Dist: prompt-toolkit (>=3.0.43)
Requires-Dist: rich (>=13.7.0)
Requires-Dist: shap (>=0.46.0,<0.47.0)
Requires-Dist: tiktoken (>=0.8.0,<0.9.0)
Project-URL: Repository, https://github.com/JanHuntersi/xai_gpt_shap
